{
  "openapi": "3.0.1",
  "info": {
    "title": "API",
    "description": "Vacations tracker API",
    "version": "v1"
  },
  "paths": {
    "/api/auth/login": {
      "get": {
        "tags": [
          "Auth"
        ],
        "responses": {
          "200": {
            "description": "Success"
          }
        }
      }
    },
    "/api/auth/forgotPassword": {
      "post": {
        "tags": [
          "Auth"
        ],
        "requestBody": {
          "content": {
            "application/json": {
              "schema": {
                "$ref": "#/components/schemas/ResetPasswordModel"
              }
            },
            "text/json": {
              "schema": {
                "$ref": "#/components/schemas/ResetPasswordModel"
              }
            },
            "application/*+json": {
              "schema": {
                "$ref": "#/components/schemas/ResetPasswordModel"
              }
            },
            "application/json-patch+json": {
              "schema": {
                "$ref": "#/components/schemas/ResetPasswordModel"
              }
            }
          }
        },
        "responses": {
          "200": {
            "description": "Success"
          }
        }
      }
    },
    "/api/auth/resetPassword": {
      "post": {
        "tags": [
          "Auth"
        ],
        "requestBody": {
          "content": {
            "application/json": {
              "schema": {
                "$ref": "#/components/schemas/ResetPasswordTokenModel"
              }
            },
            "text/json": {
              "schema": {
                "$ref": "#/components/schemas/ResetPasswordTokenModel"
              }
            },
            "application/*+json": {
              "schema": {
                "$ref": "#/components/schemas/ResetPasswordTokenModel"
              }
            },
            "application/json-patch+json": {
              "schema": {
                "$ref": "#/components/schemas/ResetPasswordTokenModel"
              }
            }
          }
        },
        "responses": {
          "200": {
            "description": "Success"
          }
        }
      }
    },
    "/api/Employee": {
      "get": {
        "tags": [
          "Employee"
        ],
        "responses": {
          "200": {
            "description": "Success",
            "content": {
              "text/plain": {
                "schema": {
                  "type": "array",
                  "items": {
                    "$ref": "#/components/schemas/EmployeeModel"
                  }
                }
              },
              "application/json": {
                "schema": {
                  "type": "array",
                  "items": {
                    "$ref": "#/components/schemas/EmployeeModel"
                  }
                }
              },
              "text/json": {
                "schema": {
                  "type": "array",
                  "items": {
                    "$ref": "#/components/schemas/EmployeeModel"
                  }
                }
              }
            }
          }
        }
      },
      "post": {
        "tags": [
          "Employee"
        ],
        "requestBody": {
          "content": {
            "application/json": {
              "schema": {
                "$ref": "#/components/schemas/EmployeeModel"
              }
            },
            "text/json": {
              "schema": {
                "$ref": "#/components/schemas/EmployeeModel"
              }
            },
            "application/*+json": {
              "schema": {
                "$ref": "#/components/schemas/EmployeeModel"
              }
            },
            "application/json-patch+json": {
              "schema": {
                "$ref": "#/components/schemas/EmployeeModel"
              }
            }
          }
        },
        "responses": {
          "200": {
            "description": "Success"
          }
        }
      },
      "put": {
        "tags": [
          "Employee"
        ],
        "requestBody": {
          "content": {
            "application/json": {
              "schema": {
                "$ref": "#/components/schemas/EmployeeModel"
              }
            },
            "text/json": {
              "schema": {
                "$ref": "#/components/schemas/EmployeeModel"
              }
            },
            "application/*+json": {
              "schema": {
                "$ref": "#/components/schemas/EmployeeModel"
              }
            },
            "application/json-patch+json": {
              "schema": {
                "$ref": "#/components/schemas/EmployeeModel"
              }
            }
          }
        },
        "responses": {
          "200": {
            "description": "Success"
          }
        }
      }
    },
    "/api/Employee/paged/{offset}/{count}": {
      "get": {
        "tags": [
          "Employee"
        ],
        "parameters": [
          {
            "name": "offset",
            "in": "path",
            "required": true,
            "schema": {
              "type": "integer",
              "format": "int32"
            }
          },
          {
            "name": "count",
            "in": "path",
            "required": true,
            "schema": {
              "type": "integer",
              "format": "int32"
            }
          }
        ],
        "responses": {
          "200": {
            "description": "Success",
            "content": {
              "text/plain": {
                "schema": {
                  "type": "array",
                  "items": {
                    "$ref": "#/components/schemas/EmployeeModel"
                  }
                }
              },
              "application/json": {
                "schema": {
                  "type": "array",
                  "items": {
                    "$ref": "#/components/schemas/EmployeeModel"
                  }
                }
              },
              "text/json": {
                "schema": {
                  "type": "array",
                  "items": {
                    "$ref": "#/components/schemas/EmployeeModel"
                  }
                }
              }
            }
          }
        }
      }
    },
    "/api/Employee/all": {
      "get": {
        "tags": [
          "Employee"
        ],
        "responses": {
          "200": {
            "description": "Success",
            "content": {
              "text/plain": {
                "schema": {
                  "type": "array",
                  "items": {
                    "$ref": "#/components/schemas/EmployeeModel"
                  }
                }
              },
              "application/json": {
                "schema": {
                  "type": "array",
                  "items": {
                    "$ref": "#/components/schemas/EmployeeModel"
                  }
                }
              },
              "text/json": {
                "schema": {
                  "type": "array",
                  "items": {
                    "$ref": "#/components/schemas/EmployeeModel"
                  }
                }
              }
            }
          }
        }
      }
    },
    "/api/Employee/all/paged/{offset}/{count}": {
      "get": {
        "tags": [
          "Employee"
        ],
        "parameters": [
          {
            "name": "offset",
            "in": "path",
            "required": true,
            "schema": {
              "type": "integer",
              "format": "int32"
            }
          },
          {
            "name": "count",
            "in": "path",
            "required": true,
            "schema": {
              "type": "integer",
              "format": "int32"
            }
          }
        ],
        "responses": {
          "200": {
            "description": "Success",
            "content": {
              "text/plain": {
                "schema": {
                  "type": "array",
                  "items": {
                    "$ref": "#/components/schemas/EmployeeModel"
                  }
                }
              },
              "application/json": {
                "schema": {
                  "type": "array",
                  "items": {
                    "$ref": "#/components/schemas/EmployeeModel"
                  }
                }
              },
              "text/json": {
                "schema": {
                  "type": "array",
                  "items": {
                    "$ref": "#/components/schemas/EmployeeModel"
                  }
                }
              }
            }
          }
        }
      }
    },
    "/api/Employee/team/{id}": {
      "get": {
        "tags": [
          "Employee"
        ],
        "parameters": [
          {
            "name": "id",
            "in": "path",
            "required": true,
            "schema": {
              "type": "string",
              "format": "uuid",
              "default": ""
            }
          }
        ],
        "responses": {
          "200": {
            "description": "Success",
            "content": {
              "text/plain": {
                "schema": {
                  "type": "array",
                  "items": {
                    "$ref": "#/components/schemas/EmployeeModel"
                  }
                }
              },
              "application/json": {
                "schema": {
                  "type": "array",
                  "items": {
                    "$ref": "#/components/schemas/EmployeeModel"
                  }
                }
              },
              "text/json": {
                "schema": {
                  "type": "array",
                  "items": {
                    "$ref": "#/components/schemas/EmployeeModel"
                  }
                }
              }
            }
          }
        }
      }
    },
    "/api/Employee/team/{id}/paged/{offset}/{count}": {
      "get": {
        "tags": [
          "Employee"
        ],
        "parameters": [
          {
            "name": "id",
            "in": "path",
            "required": true,
            "schema": {
              "type": "string",
              "format": "uuid",
              "default": ""
            }
          },
          {
            "name": "offset",
            "in": "path",
            "required": true,
            "schema": {
              "type": "integer",
              "format": "int32"
            }
          },
          {
            "name": "count",
            "in": "path",
            "required": true,
            "schema": {
              "type": "integer",
              "format": "int32"
            }
          }
        ],
        "responses": {
          "200": {
            "description": "Success",
            "content": {
              "text/plain": {
                "schema": {
                  "type": "array",
                  "items": {
                    "$ref": "#/components/schemas/EmployeeModel"
                  }
                }
              },
              "application/json": {
                "schema": {
                  "type": "array",
                  "items": {
                    "$ref": "#/components/schemas/EmployeeModel"
                  }
                }
              },
              "text/json": {
                "schema": {
                  "type": "array",
                  "items": {
                    "$ref": "#/components/schemas/EmployeeModel"
                  }
                }
              }
            }
          }
        }
      }
    },
    "/api/Employee/{id}": {
      "get": {
        "tags": [
          "Employee"
        ],
        "parameters": [
          {
            "name": "id",
            "in": "path",
            "required": true,
            "schema": {
              "type": "string",
              "format": "uuid",
              "default": ""
            }
          }
        ],
        "responses": {
          "200": {
            "description": "Success",
            "content": {
              "text/plain": {
                "schema": {
                  "$ref": "#/components/schemas/EmployeeModel"
                }
              },
              "application/json": {
                "schema": {
                  "$ref": "#/components/schemas/EmployeeModel"
                }
              },
              "text/json": {
                "schema": {
                  "$ref": "#/components/schemas/EmployeeModel"
                }
              }
            }
          }
        }
      }
    },
    "/api/Employee/{id}/state/{deleted}": {
      "put": {
        "tags": [
          "Employee"
        ],
        "parameters": [
          {
            "name": "id",
            "in": "path",
            "required": true,
            "schema": {
              "type": "string",
              "format": "uuid",
              "default": ""
            }
          },
          {
            "name": "deleted",
            "in": "path",
            "required": true,
            "schema": {
              "type": "boolean"
            }
          }
        ],
        "responses": {
          "200": {
            "description": "Success"
          }
        }
      }
    },
    "/api/Team": {
      "get": {
        "tags": [
          "Team"
        ],
        "responses": {
          "200": {
            "description": "Success",
            "content": {
              "text/plain": {
                "schema": {
                  "type": "array",
                  "items": {
                    "$ref": "#/components/schemas/TeamModel"
                  }
                }
              },
              "application/json": {
                "schema": {
                  "type": "array",
                  "items": {
                    "$ref": "#/components/schemas/TeamModel"
                  }
                }
              },
              "text/json": {
                "schema": {
                  "type": "array",
                  "items": {
                    "$ref": "#/components/schemas/TeamModel"
                  }
                }
              }
            }
          }
        }
      },
      "post": {
        "tags": [
          "Team"
        ],
        "requestBody": {
          "content": {
            "application/json": {
              "schema": {
                "$ref": "#/components/schemas/TeamModel"
              }
            },
            "text/json": {
              "schema": {
                "$ref": "#/components/schemas/TeamModel"
              }
            },
            "application/*+json": {
              "schema": {
                "$ref": "#/components/schemas/TeamModel"
              }
            },
            "application/json-patch+json": {
              "schema": {
                "$ref": "#/components/schemas/TeamModel"
              }
            }
          }
        },
        "responses": {
          "200": {
            "description": "Success",
            "content": {
              "text/plain": {
                "schema": {
                  "type": "string",
                  "format": "uuid"
                }
              },
              "application/json": {
                "schema": {
                  "type": "string",
                  "format": "uuid"
                }
              },
              "text/json": {
                "schema": {
                  "type": "string",
                  "format": "uuid"
                }
              }
            }
          }
        }
      },
      "put": {
        "tags": [
          "Team"
        ],
        "requestBody": {
          "content": {
            "application/json": {
              "schema": {
                "$ref": "#/components/schemas/TeamModel"
              }
            },
            "text/json": {
              "schema": {
                "$ref": "#/components/schemas/TeamModel"
              }
            },
            "application/*+json": {
              "schema": {
                "$ref": "#/components/schemas/TeamModel"
              }
            },
            "application/json-patch+json": {
              "schema": {
                "$ref": "#/components/schemas/TeamModel"
              }
            }
          }
        },
        "responses": {
          "200": {
            "description": "Success"
          }
        }
      }
    },
    "/api/Team/all": {
      "get": {
        "tags": [
          "Team"
        ],
        "responses": {
          "200": {
            "description": "Success",
            "content": {
              "text/plain": {
                "schema": {
                  "type": "array",
                  "items": {
                    "$ref": "#/components/schemas/TeamModel"
                  }
                }
              },
              "application/json": {
                "schema": {
                  "type": "array",
                  "items": {
                    "$ref": "#/components/schemas/TeamModel"
                  }
                }
              },
              "text/json": {
                "schema": {
                  "type": "array",
                  "items": {
                    "$ref": "#/components/schemas/TeamModel"
                  }
                }
              }
            }
          }
        }
      }
    },
    "/api/Team/{id}": {
      "get": {
        "tags": [
          "Team"
        ],
        "parameters": [
          {
            "name": "id",
            "in": "path",
            "required": true,
            "schema": {
              "type": "string",
              "format": "uuid",
              "default": ""
            }
          }
        ],
        "responses": {
          "200": {
            "description": "Success",
            "content": {
              "text/plain": {
                "schema": {
                  "$ref": "#/components/schemas/TeamModel"
                }
              },
              "application/json": {
                "schema": {
                  "$ref": "#/components/schemas/TeamModel"
                }
              },
              "text/json": {
                "schema": {
                  "$ref": "#/components/schemas/TeamModel"
                }
              }
            }
          }
        }
      }
    },
    "/api/Team/{id}/state/{deleted}": {
      "put": {
        "tags": [
          "Team"
        ],
        "parameters": [
          {
            "name": "id",
            "in": "path",
            "required": true,
            "schema": {
              "type": "string",
              "format": "uuid",
              "default": ""
            }
          },
          {
            "name": "deleted",
            "in": "path",
            "required": true,
            "schema": {
              "type": "boolean"
            }
          }
        ],
        "responses": {
          "200": {
            "description": "Success"
          }
        }
      }
    },
    "/api/Team/{id}/user/{employeeId}/add": {
      "post": {
        "tags": [
          "Team"
        ],
        "parameters": [
          {
            "name": "id",
            "in": "path",
            "required": true,
            "schema": {
              "type": "string",
              "format": "uuid",
              "default": ""
            }
          },
          {
            "name": "employeeId",
            "in": "path",
            "required": true,
            "schema": {
              "type": "string",
              "format": "uuid",
              "default": ""
            }
          }
        ],
        "responses": {
          "200": {
            "description": "Success"
          }
        }
      }
    },
    "/api/Team/{id}/user/{employeeId}/remove": {
      "post": {
        "tags": [
          "Team"
        ],
        "parameters": [
          {
            "name": "id",
            "in": "path",
            "required": true,
            "schema": {
              "type": "string",
              "format": "uuid",
              "default": ""
            }
          },
          {
            "name": "employeeId",
            "in": "path",
            "required": true,
            "schema": {
              "type": "string",
              "format": "uuid",
              "default": ""
            }
          }
        ],
        "responses": {
          "200": {
            "description": "Success"
          }
        }
      }
    },
    "/api/Transaction/{id}": {
      "get": {
        "tags": [
          "Transaction"
        ],
        "parameters": [
          {
            "name": "id",
            "in": "path",
            "required": true,
            "schema": {
              "type": "string",
              "format": "uuid",
              "default": ""
            }
          }
        ],
        "responses": {
          "200": {
            "description": "Success",
            "content": {
              "text/plain": {
                "schema": {
                  "$ref": "#/components/schemas/Transaction"
                }
              },
              "application/json": {
                "schema": {
                  "$ref": "#/components/schemas/Transaction"
                }
              },
              "text/json": {
                "schema": {
                  "$ref": "#/components/schemas/Transaction"
                }
              }
            }
          }
        }
      }
    },
    "/api/Transaction/employee/{id}": {
      "get": {
        "tags": [
          "Transaction"
        ],
        "parameters": [
          {
            "name": "employeeId",
            "in": "query",
            "schema": {
              "type": "string",
              "format": "uuid",
              "default": ""
            }
          },
          {
            "name": "id",
            "in": "path",
            "required": true,
            "schema": {
              "type": "string"
            }
          }
        ],
        "responses": {
          "200": {
            "description": "Success",
            "content": {
              "text/plain": {
                "schema": {
                  "type": "array",
                  "items": {
                    "$ref": "#/components/schemas/Transaction"
                  }
                }
              },
              "application/json": {
                "schema": {
                  "type": "array",
                  "items": {
                    "$ref": "#/components/schemas/Transaction"
                  }
                }
              },
              "text/json": {
                "schema": {
                  "type": "array",
                  "items": {
                    "$ref": "#/components/schemas/Transaction"
                  }
                }
              }
            }
          }
        }
      }
    },
    "/api/Transaction": {
      "post": {
        "tags": [
          "Transaction"
        ],
        "requestBody": {
          "content": {
            "application/json": {
              "schema": {
                "$ref": "#/components/schemas/Transaction"
              }
            },
            "text/json": {
              "schema": {
                "$ref": "#/components/schemas/Transaction"
              }
            },
            "application/*+json": {
              "schema": {
                "$ref": "#/components/schemas/Transaction"
              }
            },
            "application/json-patch+json": {
              "schema": {
                "$ref": "#/components/schemas/Transaction"
              }
            }
          }
        },
        "responses": {
          "200": {
            "description": "Success"
          }
        }
      }
    },
    "/api/Vacation": {
      "get": {
        "tags": [
          "Vacation"
        ],
        "responses": {
          "200": {
            "description": "Success",
            "content": {
              "text/plain": {
                "schema": {
                  "type": "array",
                  "items": {
                    "$ref": "#/components/schemas/VacationModel"
                  }
                }
              },
              "application/json": {
                "schema": {
                  "type": "array",
                  "items": {
                    "$ref": "#/components/schemas/VacationModel"
                  }
                }
              },
              "text/json": {
                "schema": {
                  "type": "array",
                  "items": {
                    "$ref": "#/components/schemas/VacationModel"
                  }
                }
              }
            }
          }
        }
      },
      "post": {
        "tags": [
          "Vacation"
        ],
        "requestBody": {
          "content": {
            "application/json": {
              "schema": {
                "$ref": "#/components/schemas/VacationModel"
              }
            },
            "text/json": {
              "schema": {
                "$ref": "#/components/schemas/VacationModel"
              }
            },
            "application/*+json": {
              "schema": {
                "$ref": "#/components/schemas/VacationModel"
              }
            },
            "application/json-patch+json": {
              "schema": {
                "$ref": "#/components/schemas/VacationModel"
              }
            }
          }
        },
        "responses": {
          "200": {
            "description": "Success"
          }
        }
      },
      "put": {
        "tags": [
          "Vacation"
        ],
        "requestBody": {
          "content": {
            "application/json": {
              "schema": {
                "$ref": "#/components/schemas/VacationModel"
              }
            },
            "text/json": {
              "schema": {
                "$ref": "#/components/schemas/VacationModel"
              }
            },
            "application/*+json": {
              "schema": {
                "$ref": "#/components/schemas/VacationModel"
              }
            },
            "application/json-patch+json": {
              "schema": {
                "$ref": "#/components/schemas/VacationModel"
              }
            }
          }
        },
        "responses": {
          "200": {
            "description": "Success"
          }
        }
      }
    },
    "/api/Vacation/{id}": {
      "get": {
        "tags": [
          "Vacation"
        ],
        "parameters": [
          {
            "name": "id",
            "in": "path",
            "required": true,
            "schema": {
              "type": "string",
              "format": "uuid",
              "default": ""
            }
          }
        ],
        "responses": {
          "200": {
            "description": "Success",
            "content": {
              "text/plain": {
                "schema": {
                  "$ref": "#/components/schemas/VacationModel"
                }
              },
              "application/json": {
                "schema": {
                  "$ref": "#/components/schemas/VacationModel"
                }
              },
              "text/json": {
                "schema": {
                  "$ref": "#/components/schemas/VacationModel"
                }
              }
            }
          }
        }
      },
      "delete": {
        "tags": [
          "Vacation"
        ],
        "parameters": [
          {
            "name": "id",
            "in": "path",
            "required": true,
            "schema": {
              "type": "string",
              "format": "uuid",
              "default": ""
            }
          }
        ],
        "responses": {
          "200": {
            "description": "Success"
          }
        }
      }
    },
    "/api/Vacation/employee/{id}": {
      "get": {
        "tags": [
          "Vacation"
        ],
        "parameters": [
          {
            "name": "id",
            "in": "path",
            "required": true,
            "schema": {
              "type": "string",
              "format": "uuid",
              "default": ""
            }
          }
        ],
        "responses": {
          "200": {
            "description": "Success",
            "content": {
              "text/plain": {
                "schema": {
                  "type": "array",
                  "items": {
                    "$ref": "#/components/schemas/VacationModel"
                  }
                }
              },
              "application/json": {
                "schema": {
                  "type": "array",
                  "items": {
                    "$ref": "#/components/schemas/VacationModel"
                  }
                }
              },
              "text/json": {
                "schema": {
                  "type": "array",
                  "items": {
                    "$ref": "#/components/schemas/VacationModel"
                  }
                }
              }
            }
          }
        }
      }
    },
    "/api/Vacation/team/{id}": {
      "get": {
        "tags": [
          "Vacation"
        ],
        "parameters": [
          {
            "name": "id",
            "in": "path",
            "required": true,
            "schema": {
              "type": "string",
              "format": "uuid",
              "default": ""
            }
          }
        ],
        "responses": {
          "200": {
            "description": "Success",
            "content": {
              "text/plain": {
                "schema": {
                  "type": "array",
                  "items": {
                    "$ref": "#/components/schemas/VacationModel"
                  }
                }
              },
              "application/json": {
                "schema": {
                  "type": "array",
                  "items": {
                    "$ref": "#/components/schemas/VacationModel"
                  }
                }
              },
              "text/json": {
                "schema": {
                  "type": "array",
                  "items": {
                    "$ref": "#/components/schemas/VacationModel"
                  }
                }
              }
            }
          }
        }
      }
    },
    "/api/Vacation/team/{id}/range/{from}/{to}": {
      "get": {
        "tags": [
          "Vacation"
        ],
        "parameters": [
          {
            "name": "id",
            "in": "path",
            "required": true,
            "schema": {
              "type": "string",
              "format": "uuid",
              "default": ""
            }
          },
          {
            "name": "from",
            "in": "path",
            "required": true,
            "schema": {
              "type": "string",
              "format": "date-time",
              "default": ""
            }
          },
          {
            "name": "to",
            "in": "path",
            "required": true,
            "schema": {
              "type": "string",
              "format": "date-time",
              "default": ""
            }
          }
        ],
        "responses": {
          "200": {
            "description": "Success",
            "content": {
              "text/plain": {
                "schema": {
                  "type": "array",
                  "items": {
                    "$ref": "#/components/schemas/VacationModel"
                  }
                }
              },
              "application/json": {
                "schema": {
                  "type": "array",
                  "items": {
                    "$ref": "#/components/schemas/VacationModel"
                  }
                }
              },
              "text/json": {
                "schema": {
                  "type": "array",
                  "items": {
                    "$ref": "#/components/schemas/VacationModel"
                  }
                }
              }
            }
          }
        }
      }
    },
    "/api/Vacation/pending": {
      "get": {
        "tags": [
          "Vacation"
        ],
        "responses": {
          "200": {
            "description": "Success",
            "content": {
              "text/plain": {
                "schema": {
                  "type": "array",
                  "items": {
                    "$ref": "#/components/schemas/VacationModel"
                  }
                }
              },
              "application/json": {
                "schema": {
                  "type": "array",
                  "items": {
                    "$ref": "#/components/schemas/VacationModel"
                  }
                }
              },
              "text/json": {
                "schema": {
                  "type": "array",
                  "items": {
                    "$ref": "#/components/schemas/VacationModel"
                  }
                }
              }
            }
          }
        }
      }
    },
    "/api/Vacation/{id}/status": {
      "put": {
        "tags": [
          "Vacation"
        ],
        "parameters": [
          {
            "name": "id",
            "in": "path",
            "required": true,
            "schema": {
              "type": "string",
              "format": "uuid",
              "default": ""
            }
          }
        ],
        "requestBody": {
          "content": {
            "application/json": {
              "schema": {
                "$ref": "#/components/schemas/VacationStatusChangeModel"
              }
            },
            "text/json": {
              "schema": {
                "$ref": "#/components/schemas/VacationStatusChangeModel"
              }
            },
            "application/*+json": {
              "schema": {
                "$ref": "#/components/schemas/VacationStatusChangeModel"
              }
            },
            "application/json-patch+json": {
              "schema": {
                "$ref": "#/components/schemas/VacationStatusChangeModel"
              }
            }
          }
        },
        "responses": {
          "200": {
            "description": "Success"
          }
        }
      }
    }
  },
  "components": {
    "schemas": {
      "ResetPasswordModel": {
        "type": "object",
        "properties": {
          "email": {
            "type": "string"
          },
          "date": {
            "type": "string",
            "format": "date-time"
          }
        },
        "additionalProperties": false
      },
      "ResetPasswordTokenModel": {
        "type": "object",
        "properties": {
          "token": {
            "type": "string"
          },
          "password": {
            "type": "string"
          }
        },
        "additionalProperties": false
      },
      "TeamModel": {
        "type": "object",
        "properties": {
          "id": {
            "type": "string",
            "format": "uuid",
            "nullable": true
          },
          "name": {
            "type": "string"
          },
          "teamLeadId": {
            "type": "string",
            "format": "uuid"
          },
          "deleted": {
            "type": "boolean",
            "nullable": true
          },
          "teamLeadName": {
            "type": "string"
          },
          "employeeCount": {
            "type": "integer",
            "format": "int32",
            "nullable": true
          },
          "employees": {
            "type": "array",
            "items": {
              "$ref": "#/components/schemas/EmployeeModel"
            }
          }
        },
        "additionalProperties": false
      },
      "EmployeeModel": {
        "type": "object",
        "properties": {
          "id": {
            "type": "string",
            "format": "uuid"
          },
          "firstName": {
            "type": "string"
          },
          "surname": {
            "type": "string"
          },
          "avatar": {
            "type": "string"
          },
          "birthdate": {
            "type": "string",
            "format": "date-time"
          },
          "jobTitle": {
            "type": "string"
          },
          "workEmail": {
            "type": "string"
          },
          "email": {
            "type": "string"
          },
          "phone": {
            "type": "string"
          },
          "skype": {
            "type": "string"
          },
          "workStartDate": {
            "type": "string",
            "format": "date-time"
          },
          "isActive": {
            "type": "boolean"
          },
          "workEndDate": {
            "type": "string",
            "format": "date-time",
            "nullable": true
          },
          "deleted": {
            "type": "boolean"
          },
          "balance": {
            "type": "integer",
            "format": "int32"
          },
          "teamId": {
            "type": "string",
            "format": "uuid",
            "nullable": true
          },
          "teams": {
            "type": "array",
            "items": {
              "$ref": "#/components/schemas/TeamModel"
            }
          }
        },
        "additionalProperties": false
      },
      "Vacation": {
        "type": "object",
        "properties": {
          "id": {
            "type": "string",
            "format": "uuid"
          },
          "employeeId": {
            "type": "string",
            "format": "uuid"
          },
          "startDate": {
            "type": "string",
            "format": "date-time"
          },
          "endDate": {
            "type": "string",
            "format": "date-time"
          },
          "comment": {
            "type": "string"
          },
          "approverComment": {
            "type": "string"
          },
          "approverId": {
            "type": "string",
            "format": "uuid",
            "nullable": true
          },
          "status": {
            "enum": [
              0,
              1,
              2
            ],
            "type": "integer",
            "format": "int32"
          },
          "statusChangeDate": {
            "type": "string",
            "format": "date-time",
            "nullable": true
          },
          "createDateTime": {
            "type": "string",
            "format": "date-time"
          },
          "deleted": {
            "type": "boolean"
          },
          "employee": {
            "$ref": "#/components/schemas/Employee"
          },
          "approver": {
            "$ref": "#/components/schemas/Employee"
          }
        },
        "additionalProperties": false
      },
      "Team": {
        "type": "object",
        "properties": {
          "id": {
            "type": "string",
            "format": "uuid"
          },
          "name": {
            "type": "string"
          },
          "teamLeadId": {
            "type": "string",
            "format": "uuid"
          },
          "deleted": {
            "type": "boolean"
          },
          "employeeTeams": {
            "type": "array",
            "items": {
              "$ref": "#/components/schemas/EmployeeTeam"
            }
          },
          "teamLead": {
            "$ref": "#/components/schemas/Employee"
          }
        },
        "additionalProperties": false
      },
      "EmployeeTeam": {
        "type": "object",
        "properties": {
          "id": {
            "type": "string",
            "format": "uuid"
          },
          "employeeId": {
            "type": "string",
            "format": "uuid"
          },
          "teamId": {
            "type": "string",
            "format": "uuid"
          },
          "employee": {
            "$ref": "#/components/schemas/Employee"
          },
          "team": {
            "$ref": "#/components/schemas/Team"
          }
        },
        "additionalProperties": false
      },
      "Employee": {
        "type": "object",
        "properties": {
          "id": {
            "type": "string",
            "format": "uuid"
          },
          "firstName": {
            "type": "string"
          },
          "surname": {
            "type": "string"
          },
          "avatar": {
            "type": "string"
          },
          "birthdate": {
            "type": "string",
            "format": "date-time"
          },
          "jobTitle": {
            "type": "string"
          },
          "workEmail": {
            "type": "string"
          },
          "email": {
            "type": "string"
          },
          "phone": {
            "type": "string"
          },
          "skype": {
            "type": "string"
          },
          "workStartDate": {
            "type": "string",
            "format": "date-time"
          },
          "isActive": {
            "type": "boolean"
          },
          "workEndDate": {
            "type": "string",
            "format": "date-time",
            "nullable": true
          },
          "deleted": {
            "type": "boolean"
          },
          "transactions": {
            "type": "array",
            "items": {
              "$ref": "#/components/schemas/Transaction"
            }
          },
          "vacations": {
            "type": "array",
            "items": {
              "$ref": "#/components/schemas/Vacation"
            }
          },
          "approvedVacations": {
            "type": "array",
            "items": {
              "$ref": "#/components/schemas/Vacation"
            }
          },
          "employeeTeams": {
            "type": "array",
            "items": {
              "$ref": "#/components/schemas/EmployeeTeam"
            }
          },
          "leadedTeams": {
            "type": "array",
            "items": {
              "$ref": "#/components/schemas/Team"
            }
          }
        },
        "additionalProperties": false
      },
      "Transaction": {
        "type": "object",
        "properties": {
          "id": {
            "type": "string",
            "format": "uuid"
          },
          "employeeId": {
            "type": "string",
            "format": "uuid"
          },
          "change": {
            "type": "integer",
            "format": "int32"
          },
          "comment": {
            "type": "string"
          },
          "employee": {
            "$ref": "#/components/schemas/Employee"
          }
        },
        "additionalProperties": false
      },
      "VacationModel": {
        "type": "object",
        "properties": {
          "id": {
            "type": "string",
            "format": "uuid"
          },
          "employeeId": {
            "type": "string",
            "format": "uuid"
          },
          "startDate": {
            "type": "string",
            "format": "date-time"
          },
          "endDate": {
            "type": "string",
            "format": "date-time"
          },
          "comment": {
            "type": "string"
          },
          "approverComment": {
            "type": "string"
          },
          "approverId": {
            "type": "string",
            "format": "uuid",
            "nullable": true
          },
          "status": {
            "enum": [
              0,
              1,
              2
            ],
            "type": "integer",
            "format": "int32"
          },
          "statusChangeDate": {
            "type": "string",
            "format": "date-time",
            "nullable": true
          },
          "createDateTime": {
            "type": "string",
            "format": "date-time"
          },
          "deleted": {
            "type": "boolean"
          },
          "employee": {
            "$ref": "#/components/schemas/EmployeeModel"
          },
          "approver": {
            "$ref": "#/components/schemas/EmployeeModel"
          }
        },
        "additionalProperties": false
      },
      "VacationStatusChangeModel": {
        "type": "object",
        "properties": {
          "approverComment": {
            "type": "string"
          },
          "status": {
            "enum": [
              0,
              1,
              2
            ],
            "type": "integer",
            "format": "int32"
          }
        },
        "additionalProperties": false
      }
    }
  }
}